mypy_to_codeclimate-0.0.3.dist-info/METADATA
mypy_to_codeclimate-0.0.3.dist-info/WHEEL
mypy_to_codeclimate-0.0.3.dist-info/entry_points.txt
mypy_to_codeclimate-0.0.3.dist-info/licenses/LICENSE
mypy_to_codeclimate/__init__.py
mypy_to_codeclimate/_version.py
mypy_to_codeclimate/py.typed
mypy_to_codeclimate-0.0.3.dist-info/RECORD
