Metadata-Version: 2.1
Name: mypy-to-codeclimate
Version: 0.0.3
Summary: Standalone tool to convert a mypy output to CodeQuality JSON, for Gitlab or other CIs.
Author-Email: Gabriel Dugny <mypy-to-codeclimate@dugny.me>
License: MIT
Classifier: Development Status :: 3 - Alpha
Classifier: Environment :: Console
Classifier: Intended Audience :: Developers
Classifier: License :: OSI Approved :: MIT License
Classifier: Operating System :: OS Independent
Classifier: Programming Language :: Python :: 3
Classifier: Programming Language :: Python :: 3 :: Only
Classifier: Programming Language :: Python :: 3.8
Classifier: Programming Language :: Python :: 3.9
Classifier: Programming Language :: Python :: 3.10
Classifier: Programming Language :: Python :: 3.11
Classifier: Programming Language :: Python :: 3.12
Project-URL: Repository, https://github.com/GabDug/mypy-to-codeclimate.git
Requires-Python: >=3.8
